[{"Directions":[{"key":"Driving","icon":"Driving","distance":{"text":"10.2 mi","value":16389},"duration":{"text":"27 mins","value":1638},"start_location":{"lat":41.4340977,"lng":-81.49826150000001},"end_location":{"lat":41.50055,"lng":-81.6183322},"Description":"Head <b>west</b>"},{"key":"Driving","icon":"Driving","distance":{"text":"10.2 mi","value":16389},"duration":{"text":"27 mins","value":1638},"start_location":{"lat":41.4340977,"lng":-81.49826150000001},"end_location":{"lat":41.50055,"lng":-81.6183322},"Description":"Turn <b>right</b> toward <b>Emery Rd</b>"},{"key":"Driving","icon":"Driving","distance":{"text":"10.2 mi","value":16389},"duration":{"text":"27 mins","value":1638},"start_location":{"lat":41.4340977,"lng":-81.49826150000001},"end_location":{"lat":41.50055,"lng":-81.6183322},"Description":"Turn <b>left</b> toward <b>Emery Rd</b>"},{"key":"Driving","icon":"Driving","distance":{"text":"10.2 mi","value":16389},"duration":{"text":"27 mins","value":1638},"start_location":{"lat":41.4340977,"lng":-81.49826150000001},"end_location":{"lat":41.50055,"lng":-81.6183322},"Description":"Turn <b>left</b> onto <b>Emery Rd</b>"},{"key":"Driving","icon":"Driving","distance":{"text":"10.2 mi","value":16389},"duration":{"text":"27 mins","value":1638},"start_location":{"lat":41.4340977,"lng":-81.49826150000001},"end_location":{"lat":41.50055,"lng":-81.6183322},"Description":"Turn <b>right</b> onto <b>Green Rd</b>"},{"key":"Driving","icon":"Driving","distance":{"text":"10.2 mi","value":16389},"duration":{"text":"27 mins","value":1638},"start_location":{"lat":41.4340977,"lng":-81.49826150000001},"end_location":{"lat":41.50055,"lng":-81.6183322},"Description":"Turn <b>left</b> onto <b>S Woodland Rd</b>"},{"key":"Driving","icon":"Driving","distance":{"text":"10.2 mi","value":16389},"duration":{"text":"27 mins","value":1638},"start_location":{"lat":41.4340977,"lng":-81.49826150000001},"end_location":{"lat":41.50055,"lng":-81.6183322},"Description":"Turn <b>right</b> onto <b>S Park Blvd</b>"},{"key":"Driving","icon":"Driving","distance":{"text":"10.2 mi","value":16389},"duration":{"text":"27 mins","value":1638},"start_location":{"lat":41.4340977,"lng":-81.49826150000001},"end_location":{"lat":41.50055,"lng":-81.6183322},"Description":"Turn <b>left</b> to stay on <b>S Park Blvd</b>"},{"key":"Driving","icon":"Driving","distance":{"text":"10.2 mi","value":16389},"duration":{"text":"27 mins","value":1638},"start_location":{"lat":41.4340977,"lng":-81.49826150000001},"end_location":{"lat":41.50055,"lng":-81.6183322},"Description":"Slight <b>right</b> onto <b>Martin Luther King Jr Dr</b>"},{"key":"Driving","icon":"Driving","distance":{"text":"10.2 mi","value":16389},"duration":{"text":"27 mins","value":1638},"start_location":{"lat":41.4340977,"lng":-81.49826150000001},"end_location":{"lat":41.50055,"lng":-81.6183322},"Description":"Turn <b>left</b> onto <b>Carnegie Ave</b>"},{"key":"Driving","icon":"Driving","distance":{"text":"10.2 mi","value":16389},"duration":{"text":"27 mins","value":1638},"start_location":{"lat":41.4340977,"lng":-81.49826150000001},"end_location":{"lat":41.50055,"lng":-81.6183322},"Description":"Slight <b>right</b> to stay on <b>Carnegie Ave</b>"},{"key":"Driving","icon":"Driving","distance":{"text":"10.2 mi","value":16389},"duration":{"text":"27 mins","value":1638},"start_location":{"lat":41.4340977,"lng":-81.49826150000001},"end_location":{"lat":41.50055,"lng":-81.6183322},"Description":"Turn <b>left</b> onto <b>E 100th St</b>"}],"Heading":"Driving"},{"Directions":[{"shortestPath":{"title":"Street level","url":"1269-thestreetlevel.svg","description":"","pathpoints":"2867,2176 2896,2176 2927,2176 3333,2176 3333,2136 3333,2111","floorid":19137},"key":"Step 1 - E 100th St P2 Parking Garage","ShortNote":"Walking time: 5 minutes","Note":"Estimated walking time is 5 minutes","icon":"Parking","distance":0,"Direction":"CONTINUE","Description":"Proceed into parking garage (Go 408ft.)","path":"2867,2176 2896,2176 "},{"shortestPath":{"title":"Street level","url":"1269-thestreetlevel.svg","description":"","pathpoints":"2867,2176 2896,2176 2927,2176 3333,2176 3333,2136 3333,2111","floorid":19137},"key":"Step 1 - E 100th St P2 Parking Garage","ShortNote":"Walking time: 5 minutes","Note":"Estimated walking time is 5 minutes","icon":"Parking","distance":408,"Direction":"LEFT","Description":"Park your vehicle (Go 57ft.)","path":"2927,2176 3333,2176 "},{"shortestPath":{"title":"Street level","url":"1269-thestreetlevel.svg","description":"","pathpoints":"2867,2176 2896,2176 2927,2176 3333,2176 3333,2136 3333,2111","floorid":19137},"key":"Step 1 - E 100th St P2 Parking Garage","ShortNote":"Walking time: 5 minutes","Note":"Estimated walking time is 5 minutes","icon":"Parking","distance":57,"Direction":"PARKING","Description":"Arrive at Recommended Parking Location","path":"3333,2136 3333,2111 "}],"Heading":"Street level"},{"Directions":[{"shortestPath":{"title":"Street level","url":"1269-thestreetlevel.svg","description":"","pathpoints":"3333,2111 3125,2111 2938,2111","floorid":19137},"key":"Step 2 - Street level","ShortNote":"Walking time: 5 minutes","Note":"Estimated walking time is 5 minutes","icon":"Walking","distance":0,"Direction":"FLOOR-FLOOR","Description":"Take the P2 elevator to the skyway level","path":"2938,2111 2949,2098 "}],"Heading":"Street level"},{"Directions":[{"shortestPath":{"title":"Skyway level","url":"1269-theskywaylevel.svg","description":"","pathpoints":"2949,2098 2943,2098 2933,2098 2933,2075 2933,1910 2933,1846 2933,1817.80004882813 2933,1753 2933,1735 2967,1735 2996,1735","floorid":19136},"key":"Step 3 - Skyway level","ShortNote":"Walking time: 5 minutes","Note":"Estimated walking time is 5 minutes","icon":"Walking","distance":0,"Direction":"CONTINUE","Description":"Continue onto the Skyway (Go 14ft.)","path":"2949,2098 2943,2098 "},{"shortestPath":{"title":"Skyway level","url":"1269-theskywaylevel.svg","description":"","pathpoints":"2949,2098 2943,2098 2933,2098 2933,2075 2933,1910 2933,1846 2933,1817.80004882813 2933,1753 2933,1735 2967,1735 2996,1735","floorid":19136},"key":"Step 3 - Skyway level","ShortNote":"Walking time: 5 minutes","Note":"Estimated walking time is 5 minutes","icon":"Walking","distance":14,"Direction":"RIGHT","Description":"Turn right and take the Skyway towards the Main Hospital (Go 319ft.)","path":"2943,2098 2933,2098 "},{"shortestPath":{"title":"Skyway level","url":"1269-theskywaylevel.svg","description":"","pathpoints":"2949,2098 2943,2098 2933,2098 2933,2075 2933,1910 2933,1846 2933,1817.80004882813 2933,1753 2933,1735 2967,1735 2996,1735","floorid":19136},"key":"Step 3 - Skyway level","ShortNote":"Walking time: 5 minutes","Note":"Estimated walking time is 5 minutes","icon":"Walking","distance":319,"Direction":"RIGHT","Description":"Turn right towards the Crile building (A) (Go 55ft.)","path":"2933,1753 2933,1735 "},{"shortestPath":{"title":"Skyway level","url":"1269-theskywaylevel.svg","description":"","pathpoints":"2949,2098 2943,2098 2933,2098 2933,2075 2933,1910 2933,1846 2933,1817.80004882813 2933,1753 2933,1735 2967,1735 2996,1735","floorid":19136},"key":"Step 3 - Skyway level","ShortNote":"Walking time: 5 minutes","Note":"Estimated walking time is 5 minutes","icon":"Walking","distance":0,"Direction":"FLOOR-FLOOR","Description":"Take the Stairway or elevator to the first floor","path":"2996,1735 3001,1616 "}],"Heading":"Skyway level"},{"Directions":[{"shortestPath":{"title":"First floor","url":"1269-thefirstfloor.svg","description":"","pathpoints":"3001,1616 3000,1591 3002,1563 3021,1533 3030,1520","floorid":19128},"key":"Step 4 - First floor","ShortNote":"Walking time: 5 minutes","Note":"Estimated walking time is 5 minutes","icon":"Walking","distance":0,"Direction":"CONTINUE","Description":"Continue to the Information Desk (A) (Go 47ft.)","path":"3001,1616 3000,1591 "},{"shortestPath":{"title":"First floor","url":"1269-thefirstfloor.svg","description":"","pathpoints":"3001,1616 3000,1591 3002,1563 3021,1533 3030,1520","floorid":19128},"key":"Step 4 - First floor","ShortNote":"Walking time: 5 minutes","Note":"Estimated walking time is 5 minutes","icon":"Walking","distance":47,"Direction":"SLIGHT RIGHT","Description":"Turn slight right towards Desk A12 (Go 45ft.)","path":"3000,1591 3002,1563 "},{"shortestPath":{"title":"First floor","url":"1269-thefirstfloor.svg","description":"","pathpoints":"3001,1616 3000,1591 3002,1563 3021,1533 3030,1520","floorid":19128},"key":"Step 4 - First floor","ShortNote":"Walking time: 5 minutes","Note":"Estimated walking time is 5 minutes","icon":"Walking","distance":45,"Direction":"Arrive at Destination","Description":"Arrive at Destination","path":"3021,1533 3030,1520 "}],"Heading":"First floor"}]